odoo/addons/l10n_br_sped_base/README.rst
odoo/addons/l10n_br_sped_base/__init__.py
odoo/addons/l10n_br_sped_base/__manifest__.py
odoo/addons/l10n_br_sped_base/i18n/l10n_br_sped_base.pot
odoo/addons/l10n_br_sped_base/i18n/pt.po
odoo/addons/l10n_br_sped_base/models/__init__.py
odoo/addons/l10n_br_sped_base/models/sped_declaration.py
odoo/addons/l10n_br_sped_base/models/sped_mixin.py
odoo/addons/l10n_br_sped_base/readme/CONTRIBUTORS.rst
odoo/addons/l10n_br_sped_base/readme/DESCRIPTION.rst
odoo/addons/l10n_br_sped_base/static/description/icon.png
odoo/addons/l10n_br_sped_base/static/description/index.html
odoo/addons/l10n_br_sped_base/tests/__init__.py
odoo/addons/l10n_br_sped_base/tests/demo_fake.txt
odoo/addons/l10n_br_sped_base/tests/sped_fake.py
odoo/addons/l10n_br_sped_base/tests/sped_fake_spec_9.py
odoo/addons/l10n_br_sped_base/tests/sped_mixin_fake.py
odoo/addons/l10n_br_sped_base/tests/test_sped_base.py
odoo/addons/l10n_br_sped_base/views/sped_base.xml
odoo14_addon_l10n_br_sped_base-14.0.1.0.1.dev22.dist-info/METADATA
odoo14_addon_l10n_br_sped_base-14.0.1.0.1.dev22.dist-info/WHEEL
odoo14_addon_l10n_br_sped_base-14.0.1.0.1.dev22.dist-info/top_level.txt
odoo14_addon_l10n_br_sped_base-14.0.1.0.1.dev22.dist-info/RECORD
